{
  "graphType": "multiLineChart",
  "dataSettings": {
    "dataURL": "/data/line-chart.csv",
    "fileType": "csv"
  },
  "graphDataConfiguration": [
    {
      "chartConfigId": "y",
      "columnId": ["AFG", "ARM", "ARG", "KHM", "COG"]
    },
    {
      "chartConfigId": "date",
      "columnId": "Year"
    }
  ],
  "graphSettings": {
    "graphID": "Graph-ID",
    "graphTitle": "Multi-line Chart",
    "graphDescription": "Human Development Index, 2020",
    "footNote": "",
    "sources":[
      {
        "source": "UNDP",
        "link": "https://hdr.undp.org/"
      }
    ],
    "width": 800,
    "height": 600,
    "minHeight": 400,
    "relativeHeight": 1.2,
    "padding": "16px",
    "topMargin": 64,
    "bottomMargin": 24,
    "noOfXTicks": 5,
    "leftMargin": 24,
    "rightMargin": 40,
    "suffix": "",
    "prefix": "",
    "mode": "light",
    "backgroundColor": "#FAFAFA",
    "colors": ["#006eb5", "#5DD4F0", "#02A38A", "#E78625", "#E0529E"],
    "labels": ["AFG", "ARM", "ARG", "KHM", "COG"],
    "showColorLegendAtTop": true,
    "colorLegendTitle": "Countries",
    "highlightedLines": ["AFG", "ARM", "ARG", "KHM", "COG"],
    "showValues": false,
    "maxValue": 1,
    "minValue": 0,
    "refValues": [{ "value": 16, "text": "Reference", "color": "#000" }],
    "highlightAreaSettings": [2000, 2010],
    "customHighlightAreaSettings": [
      {
        "coordinates": [
          "xValue",
          "yValue",
          "xValue",
          "yValue",
          "xValue",
          "yValue"
        ],
        "color": "#EDEFF0",
        "strokeWidth": 2,
        "dashedStroke": true
      }
    ],
    "highlightAreaColor": "#EDEFF0",
    "animateLine": false,
    "strokeWidth": 2,
    "showDots": false,
    "annotations": [
      {
        "text": "This is annotation",
        "maxWidth": 100,
        "xCoordinate": "2023",
        "yCoordinate": 12,
        "xOffset": 0,
        "yOffset": 0,
        "align": "left",
        "color": "#000",
        "fontWeight": "regular",
        "showConnector": false,
        "connectorRadius": 0
      }
    ],
    "tooltip": "Country A: {{data.y[0]}}<br>Country B: {{data.y[1]}}<br><...>",
    "graphDownload": true,
    "dataDownload": true,
    "rtl": false,
    "language": "en",
    "dateFormat": "yyyy"
  }
}
